gmail8/__init__.py
gmail8/gmail.py
gmail8/reminder.py
gmail8-0.0.2.dist-info/LICENSE
gmail8-0.0.2.dist-info/METADATA
gmail8-0.0.2.dist-info/WHEEL
gmail8-0.0.2.dist-info/top_level.txt
gmail8-0.0.2.dist-info/RECORD
