Metadata-Version: 2.1
Name: gmail8
Version: 0.0.2
Summary: A decorator
Home-page: https://github.com/gaojunbin/gmail8.git
Author: Junbin Gao
Author-email: gao.junbin.cn@gmail.com
License: Apache License 2.0
License-File: LICENSE
Requires-Dist: requests
Requires-Dist: smtplib
Requires-Dist: email
